reskinner/__init__.py
reskinner/__main__.py
reskinner/__version__.py
reskinner/colorizer.py
reskinner/constants.py
reskinner/default_window.py
reskinner/easing.py
reskinner/elements.py
reskinner/interpolation.py
reskinner/reskinner.py
reskinner/sg.py
reskinner-4.0.1.dist-info/WHEEL
reskinner-4.0.1.dist-info/METADATA
reskinner-4.0.1.dist-info/RECORD
