Metadata-Version: 2.3
Name: reskinner
Version: 4.0.1
Summary: Instantaneous theme changing for PySimpleGUI and FreeSimpleGUI windows.
Keywords: PySimpleGUI,FreeSimpleGUI,reskin,realtime,theme,color,gui
Author: Divine U. Afam-Ifediogor
License: MIT License
Classifier: Development Status :: 6 - Mature
Classifier: Framework :: PySimpleGUI
Classifier: Framework :: PySimpleGUI :: 4
Classifier: Framework :: PySimpleGUI :: 5
Classifier: License :: OSI Approved :: MIT License
Classifier: Natural Language :: English
Classifier: Programming Language :: Python
Classifier: Programming Language :: Python :: 3
Classifier: Programming Language :: Python :: 3.7
Classifier: Programming Language :: Python :: 3.8
Classifier: Programming Language :: Python :: 3.9
Classifier: Programming Language :: Python :: 3.10
Classifier: Programming Language :: Python :: 3.11
Classifier: Programming Language :: Python :: 3.12
Classifier: Programming Language :: Python :: 3.13
Classifier: Programming Language :: Python :: 3.14
Requires-Dist: colour>=0.1.5
Requires-Dist: strenum ; python_full_version < '3.11'
Requires-Dist: importlib-metadata ; python_full_version < '3.8'
Requires-Dist: typing-extensions ; python_full_version < '3.8'
Requires-Dist: freesimplegui>=5.0.0 ; extra == 'fsg'
Requires-Dist: pysimplegui>=4.60.3.96 ; extra == 'psg'
Requires-Python: >=3.7
Project-URL: Bug Tracker, https://github.com/definite-d/psg_reskinner/issues/
Project-URL: Homepage, https://github.com/definite-d/psg_reskinner/
Provides-Extra: fsg
Provides-Extra: psg
